pypc/settings.py
pypc/__init__.py
pypc/create.py
pypc/cli.py
pypc/templates/CHANGES
pypc/templates/README
pypc/templates/setup.html
pypc/templates/__init__.pyc
pypc/templates/setup.cfg
pypc/templates/header.html
pypc/templates/__init__.py
pypc/templates/LICENSE
pypc/templates/MANIFEST.in
pypc/templates/__init__.html
pypc-0.1.50.dist-info/DESCRIPTION.rst
pypc-0.1.50.dist-info/METADATA
pypc-0.1.50.dist-info/WHEEL
pypc-0.1.50.dist-info/top_level.txt
pypc-0.1.50.dist-info/entry_points.txt
pypc-0.1.50.dist-info/metadata.json
pypc-0.1.50.dist-info/RECORD
