Metadata-Version: 2.0
Name: pypc
Version: 0.1.50
Summary: Python3 Package Creator
Home-page: http://github.com/mekarpeles/pypc
Author: Mek Karpeles
Author-email: michael.karpeles@gmail.com
License: LICENSE
Keywords: pypc package creator pip
Platform: any
Classifier: Development Status :: 2 - Pre-Alpha
Classifier: Intended Audience :: Developers
Classifier: License :: OSI Approved :: MIT License
Classifier: Topic :: Software Development :: Build Tools
Classifier: Programming Language :: Python
Classifier: Programming Language :: Python :: 2
Classifier: Programming Language :: Python :: 2.7
Classifier: Programming Language :: Python :: 3
Classifier: Programming Language :: Python :: 3.4
Requires-Dist: jinja2
Requires-Dist: virtualenv
Requires-Dist: argparse; python_version=="2.7"
